Documentation/EGADS Lineage Algorithm Handbook - v1.2.8.pdf
Documentation/EGADS Lineage Documentation - v1.2.8.pdf
Documentation/changelog.txt
Documentation/EGADS Algorithm Handbook - LATEX/EGADS_alg_doc.tex
Documentation/EGADS Algorithm Handbook - LATEX/example.py
Documentation/EGADS Algorithm Handbook - LATEX/fancyvrb.cfg
Documentation/EGADS Algorithm Handbook - LATEX/pagesetup.cfg
Documentation/EGADS Algorithm Handbook - LATEX/algorithms/algorithm_template.tex
Documentation/EGADS Algorithm Handbook - LATEX/algorithms/biophysics/CAI.tex
Documentation/EGADS Algorithm Handbook - LATEX/algorithms/biophysics/CSI2.tex
Documentation/EGADS Algorithm Handbook - LATEX/algorithms/biophysics/DGVI1.tex
Documentation/EGADS Algorithm Handbook - LATEX/algorithms/biophysics/DGVI2.tex
Documentation/EGADS Algorithm Handbook - LATEX/algorithms/biophysics/DWSI5.tex
Documentation/EGADS Algorithm Handbook - LATEX/algorithms/biophysics/GI.tex
Documentation/EGADS Algorithm Handbook - LATEX/algorithms/biophysics/LCI.tex
Documentation/EGADS Algorithm Handbook - LATEX/algorithms/biophysics/LWVI1.tex
Documentation/EGADS Algorithm Handbook - LATEX/algorithms/biophysics/LWVI2.tex
Documentation/EGADS Algorithm Handbook - LATEX/algorithms/biophysics/MCARI.tex
Documentation/EGADS Algorithm Handbook - LATEX/algorithms/biophysics/NDLI.tex
Documentation/EGADS Algorithm Handbook - LATEX/algorithms/biophysics/NDNI.tex
Documentation/EGADS Algorithm Handbook - LATEX/algorithms/biophysics/NDVI.tex
Documentation/EGADS Algorithm Handbook - LATEX/algorithms/biophysics/NDWI.tex
Documentation/EGADS Algorithm Handbook - LATEX/algorithms/biophysics/NDWI_MIR.tex
Documentation/EGADS Algorithm Handbook - LATEX/algorithms/biophysics/PRI.tex
Documentation/EGADS Algorithm Handbook - LATEX/algorithms/biophysics/REIP.tex
Documentation/EGADS Algorithm Handbook - LATEX/algorithms/biophysics/RVI.tex
Documentation/EGADS Algorithm Handbook - LATEX/algorithms/biophysics/SR705.tex
egads_lineage-1.2.9.dist-info/LICENSE.txt
egads_lineage-1.2.9.dist-info/METADATA
egads_lineage-1.2.9.dist-info/WHEEL
egads_lineage-1.2.9.dist-info/top_level.txt
egads_lineage-1.2.9.dist-info/RECORD
