Metadata-Version: 2.1
Name: egads-lineage
Version: 1.2.9
Summary: EGADS: EUFAR General Airborne Data-processing Software
Home-page: https://github.com/EUFAR/egads/tree/Lineage
Download-URL: https://github.com/EUFAR/egads/tree/Lineage
Author: EUFAR, Olivier Henry
Author-email: 
Maintainer: Olivier Henry
Maintainer-email: 
License: GNU General Public License v3 (GPLv3)
Project-URL: Documentation, https://egads.readthedocs.io/en/lineage/
Keywords: airbornescience,netcdf,nasa-ames,eufar,science,microphysics,thermodynamics
Platform: Windows
Platform: Linux
Platform: MacOS
Classifier: Development Status :: 5 - Production/Stable
Classifier: Environment :: Console
Classifier: Intended Audience :: Developers
Classifier: Intended Audience :: Education
Classifier: Intended Audience :: Science/Research
Classifier: License :: OSI Approved :: GNU General Public License v3 (GPLv3)
Classifier: Natural Language :: English
Classifier: Programming Language :: Python
Classifier: Topic :: Scientific/Engineering :: Atmospheric Science
Requires: numpy (>=1.14)
Requires: netCDF4 (>=1.3.0)
Requires: python_dateutil (>=2.6.1)
Requires: quantities (>=0.12.1)
Requires: h5py (>=2.10.0)
License-File: LICENSE.txt
Requires-Dist: numpy >=1.14
Requires-Dist: netCDF4 >=1.3.0
Requires-Dist: python-dateutil >=2.6.1
Requires-Dist: quantities >=0.12.1
Requires-Dist: h5py >=2.10.0
